{"Table": "ssdfi", "Key": {"Column": "md5", "Increment": false}, "Column": [{"Field": "md5", "Type": "string", "Length": 100, "Precision": 0, "Scale": 0, "MaxNumber": 9999.0, "MinNumber": 0.0, "Nullable": false, "Comment": "编号", "Selected": []}, {"Field": "allsat_l3_path", "Type": "string", "Length": 200, "Precision": 0, "Scale": 0, "MaxNumber": 9999.0, "MinNumber": 0.0, "Nullable": true, "Comment": "输入文件路径", "Selected": []}, {"Field": "allsat_l3_nc", "Type": "string", "Length": 200, "Precision": 0, "Scale": 0, "MaxNumber": 9999.0, "MinNumber": 0.0, "Nullable": true, "Comment": "输入文件名", "Selected": []}, {"Field": "lat_max", "Type": "string", "Length": 200, "Precision": 0, "Scale": 0, "MaxNumber": 9999.0, "MinNumber": 0.0, "Nullable": true, "Comment": "最大纬度", "Selected": []}, {"Field": "lat_min", "Type": "string", "Length": 200, "Precision": 0, "Scale": 0, "MaxNumber": 9999.0, "MinNumber": 0.0, "Nullable": true, "Comment": "最小纬度", "Selected": []}, {"Field": "lon_max", "Type": "string", "Length": 200, "Precision": 0, "Scale": 0, "MaxNumber": 9999.0, "MinNumber": 0.0, "Nullable": true, "Comment": "最大经度", "Selected": []}, {"Field": "lon_min", "Type": "string", "Length": 200, "Precision": 0, "Scale": 0, "MaxNumber": 9999.0, "MinNumber": 0.0, "Nullable": true, "Comment": "最小经度", "Selected": []}, {"Field": "msla_result", "Type": "string", "Length": 200, "Precision": 0, "Scale": 0, "MaxNumber": 9999.0, "MinNumber": 0.0, "Nullable": true, "Comment": "输出文件", "Selected": []}, {"Field": "xml_path", "Type": "string", "Length": 200, "Precision": 0, "Scale": 0, "MaxNumber": 9999.0, "MinNumber": 0.0, "Nullable": true, "Comment": "XML文件路径", "Selected": []}, {"Field": "create_time", "Type": "datetime", "Length": 0, "Precision": 0, "Scale": 0, "MaxNumber": 9999.0, "MinNumber": 0.0, "Nullable": true, "Comment": "创建时间", "Selected": []}, {"Field": "extend1", "Type": "string", "Length": 100, "Precision": 0, "Scale": 0, "MaxNumber": 9999.0, "MinNumber": 0.0, "Nullable": true, "Comment": "扩展字段1", "Selected": []}, {"Field": "extend2", "Type": "string", "Length": 100, "Precision": 0, "Scale": 0, "MaxNumber": 9999.0, "MinNumber": 0.0, "Nullable": true, "Comment": "扩展字段2", "Selected": []}, {"Field": "extend3", "Type": "string", "Length": 100, "Precision": 0, "Scale": 0, "MaxNumber": 9999.0, "MinNumber": 0.0, "Nullable": true, "Comment": "扩展字段3", "Selected": []}, {"Field": "extend4", "Type": "string", "Length": 100, "Precision": 0, "Scale": 0, "MaxNumber": 9999.0, "MinNumber": 0.0, "Nullable": true, "Comment": "扩展字段4", "Selected": []}, {"Field": "extend5", "Type": "string", "Length": 100, "Precision": 0, "Scale": 0, "MaxNumber": 9999.0, "MinNumber": 0.0, "Nullable": true, "Comment": "扩展字段5", "Selected": []}], "QueryCount": 0}